cwmeda/__init__.py
cwmeda-0.0.2.dist-info/licenses/LICENSE
cwmeda-0.0.2.dist-info/METADATA
cwmeda-0.0.2.dist-info/WHEEL
cwmeda-0.0.2.dist-info/top_level.txt
cwmeda-0.0.2.dist-info/RECORD
